PotMail/PotMail.py
PotMail/__init__.py
PotMail-1.0.dist-info/METADATA
PotMail-1.0.dist-info/WHEEL
PotMail-1.0.dist-info/top_level.txt
PotMail-1.0.dist-info/RECORD
